Workbook

Sheet Previsão Financeira
A2: PREVISÃO FINANCEIRA SEMANAL
B3: SEGUNDA | C3: TERÇA | D3: QUARTA | E3: QUINTA | F3: SEXTA
B4: 46293 | C4: 46294 | D4: 46295 | E4: 46296 | F4: 46297
A6: SALDO INICIAL | B6: 50000
A8: CONTAS À RECEBER
A9: BANRISUL COBRANCA | B9: 52789.7 | C9: 92480.79 | D9: 93660.7 | E9: 89104.97 | F9: 80640.07
A10: BRADESCO COBRANCA | B10: 216519.53 | C10: 191447.63 | D10: 241060.2 | E10: 224287.16 | F10: 182089.12
A11: CARTORIO | B11: 0 | C11: 0 | D11: 0 | E11: 0 | F11: 0
A12: CONTAS A RECEBER | B12: 0 | C12: 73 | D12: 491.1 | E12: 1204.87 | F12: 0
A13: CONTAS À PAGAR | B13: =B23 -> 195926.6 | C13: =B27 -> 141628.96 | D13: =B33 -> 57487.24 | E13: =B38 -> 92943.66 | F13: =B43 -> 69471.61
B14: 0 | C14: 0 | D14: 0 | E14: 0 | F14: 0
A15: SALDO | B15: =B6+B18-B13 | C15: =B15+C18-C13 | D15: =C15+D18-D13 | E15: =D15+E18-E13 | F15: =E15+F18-F13
A16: FUNCIONARIOS | B16: 0 | C16: 0 | D16: 0 | E16: 0 | F16: 0
A17: PROTESTO | B17: 0 | C17: 0 | D17: 0 | E17: 0 | F17: 0
A18: Total | B18: =SUM(B9:B17) | C18: =SUM(C9:C17) | D18: =SUM(D9:D17) | E18: =SUM(E9:E17) | F18: =SUM(F9:F17)
A19: =B4 -> 46293
A20: CONTAS A PAGAR (2) | B20: 192995.62
A21: HONORARIOS ADVOC A PAGAR (99) | B21: 401.34
A22: SEGUROS A PAGAR (51) | B22: 2529.64
A23: Total | B23: =SUM(B20:B22) -> 195926.6
A25: =C4 -> 46294
A26: CONTAS A PAGAR (2) | B26: 141628.96
A27: Total | B27: =SUM(B26:B26) -> 141628.96
A29: =D4 -> 46295
A30: CONTAS A PAGAR (2) | B30: 52834.35
A31: ISS RETIDO A RECOLHER (22) | B31: 118.27
A32: PARCEL FEDERAL 102024 (89) | B32: 4534.62
A33: Total | B33: =SUM(B30:B32) -> 57487.24
A35: =E4 -> 46296
A36: CONTAS A PAGAR (2) | B36: 91093.66
A37: INDENIZACOES TRABALHISTAS (49) | B37: 1850
A38: Total | B38: =SUM(B36:B37) -> 92943.66
A40: =F4 -> 46297
A41: CONTAS A PAGAR (2) | B41: 64951.29
A42: FGTS A RECOLHER (13) | B42: 4520.32
A43: Total | B43: =SUM(B41:B42) -> 69471.61

Sheet Planilha1
A2: PREVISÃO FINANCEIRA SEMANAL
B3: 28/09 - Segunda-Feira | C3: 29/09 - Terça-Feira | D3: 30/09 - Quarta-Feira | E3: 01/10 - Quinta-Feira | F3: 02/10 - Sexta-Feira
B4: 46293 | C4: 46294 | D4: 46295 | E4: 46296 | F4: 46297
A6: SALDO INICIAL | B6: 50000
A8: CONTAS À RECEBER | B8: =SUMIF(Detalhamento!$G:$G,B$4,Detalhamento!$F:$F) -> 17311.84 | C8: =SUMIF(Detalhamento!$G:$G,C$4,Detalhamento!$F:$F) -> 32227.29 | D8: =SUMIF(Detalhamento!$G:$G,D$4,Detalhamento!$F:$F) -> 300774.65 | E8: =SUMIF(Detalhamento!$G:$G,E$4,Detalhamento!$F:$F) -> 298480.96 | F8: =SUMIF(Detalhamento!$G:$G,F$4,Detalhamento!$F:$F) -> 290473.81
A9: Cobrança Bradesc | B9: =SUMIFS(Detalhamento!$F:$F,Detalhamento!$G:$G,B$4,Detalhamento!$B:$B,"BRADESCO COBRANCA") -> 16639.84 | C9: =SUMIFS(Detalhamento!$F:$F,Detalhamento!$G:$G,C$4,Detalhamento!$B:$B,"BRADESCO COBRANCA") -> 24829.04 | D9: =SUMIFS(Detalhamento!$F:$F,Detalhamento!$G:$G,D$4,Detalhamento!$B:$B,"BRADESCO COBRANCA") -> 225371.25 | E9: =SUMIFS(Detalhamento!$F:$F,Detalhamento!$G:$G,E$4,Detalhamento!$B:$B,"BRADESCO COBRANCA") -> 209762.49 | F9: =SUMIFS(Detalhamento!$F:$F,Detalhamento!$G:$G,F$4,Detalhamento!$B:$B,"BRADESCO COBRANCA") -> 174593.03
A10: Cobrança Banrisul | B10: =SUMIFS(Detalhamento!$F:$F,Detalhamento!$G:$G,B$4,Detalhamento!$B:$B,"BANRISUL COBRANCA") -> 672 | C10: =SUMIFS(Detalhamento!$F:$F,Detalhamento!$G:$G,C$4,Detalhamento!$B:$B,"BANRISUL COBRANCA") -> 7325.25 | D10: =SUMIFS(Detalhamento!$F:$F,Detalhamento!$G:$G,D$4,Detalhamento!$B:$B,"BANRISUL COBRANCA") -> 68312.3 | E10: =SUMIFS(Detalhamento!$F:$F,Detalhamento!$G:$G,E$4,Detalhamento!$B:$B,"BANRISUL COBRANCA") -> 77350.2 | F10: =SUMIFS(Detalhamento!$F:$F,Detalhamento!$G:$G,F$4,Detalhamento!$B:$B,"BANRISUL COBRANCA") -> 77668.78
A11: Depósito Clientes | B11: =SUMIFS(Detalhamento!$F:$F,Detalhamento!$G:$G,B$4,Detalhamento!$B:$B,"DEPOSITO (CLIENTE)") -> 0 | C11: =SUMIFS(Detalhamento!$F:$F,Detalhamento!$G:$G,C$4,Detalhamento!$B:$B,"DEPOSITO (CLIENTE)") -> 0 | D11: =SUMIFS(Detalhamento!$F:$F,Detalhamento!$G:$G,D$4,Detalhamento!$B:$B,"DEPOSITO (CLIENTE)") -> 6600 | E11: =SUMIFS(Detalhamento!$F:$F,Detalhamento!$G:$G,E$4,Detalhamento!$B:$B,"DEPOSITO (CLIENTE)") -> 10241.4 | F11: =SUMIFS(Detalhamento!$F:$F,Detalhamento!$G:$G,F$4,Detalhamento!$B:$B,"DEPOSITO (CLIENTE)") -> 38212
A12: Outras carteiras | B12: =B8-B9-B10-B11 -> 0 | C12: =C8-C9-C10-C11 -> 73 | D12: =D8-D9-D10-D11 -> 491.1 | E12: =E8-E9-E10-E11 -> 1126.87 | F12: =F8-F9-F10-F11 -> 0
A13: CONTAS À PAGAR | B13: =SUMIFS(Detalhamento!$H:$H,Detalhamento!$A:$A,B$4,Detalhamento!$D:$D,"*FORNECED*")+SUMIFS(Detalhamento!$H:$H,Detalhamento!$A:$A,B$4,Detalhamento!$D:$D,"*IMPOSTOS*") -> 46172.5 | C13: =SUMIFS(Detalhamento!$H:$H,Detalhamento!$A:$A,C$4,Detalhamento!$D:$D,"*FORNECED*")+SUMIFS(Detalhamento!$H:$H,Detalhamento!$A:$A,C$4,Detalhamento!$D:$D,"*IMPOSTOS*") -> 149305.93 | D13: =SUMIFS(Detalhamento!$H:$H,Detalhamento!$A:$A,D$4,Detalhamento!$D:$D,"*FORNECED*")+SUMIFS(Detalhamento!$H:$H,Detalhamento!$A:$A,D$4,Detalhamento!$D:$D,"*IMPOSTOS*") -> 62395.3 | E13: =SUMIFS(Detalhamento!$H:$H,Detalhamento!$A:$A,E$4,Detalhamento!$D:$D,"*FORNECED*")+SUMIFS(Detalhamento!$H:$H,Detalhamento!$A:$A,E$4,Detalhamento!$D:$D,"*IMPOSTOS*") -> 92943.66 | F13: =SUMIFS(Detalhamento!$H:$H,Detalhamento!$A:$A,F$4,Detalhamento!$D:$D,"*FORNECED*")+SUMIFS(Detalhamento!$H:$H,Detalhamento!$A:$A,F$4,Detalhamento!$D:$D,"*IMPOSTOS*") -> 77091.29
A15: SALDO | B15: =B6+B8-B13 -> 21139.34 | C15: =B15+C8-C13 -> -95939.3 | D15: =C15+D8-D13 -> 142440.05 | E15: =D15+E8-E13 -> 347977.35 | F15: =E15+F8-F13 -> 561359.87
A17: CONTAS À PAGAR
A19: =B3 -> 28/09 - Segunda-Feira
A20: PRF4SISTEMAS | B20: ADVOCACIA GERAL DA UNIAO | C20: 401.34
A21: 221608 | B21: CEREALISTA SERIEMA LTDA | C21: 25894.05
A22: 786 | B22: KOSTER & MATSCHINSKE LTDA - ME | C22: 11826
A23: 221599 | B23: RODRIGO CRISTIANO MICHALSKI IRGANG | C23: 7928.62
A24: 2172049 | B24: TECON RIO GRANDE S/A | C24: 122.49
A25: Total | C25: =SUM(C20:C24) -> 46172.5
A27: =C3 -> 29/09 - Terça-Feira
A28: 19600044 FT | B28: EXPRESSO SAO MIGUEL S/A | C28: 55824.94
A29: 2499391 FT | B29: FL BRASIL HOLDING LOGISTICA E TRANSPORTE | C29: 17315.46
A30: 16 | B30: GILSON SAMPAIO RIBEIRO REPRESENTACOES | C30: 66.73
A31: 95565 | B31: GLOBALFOOD SISTEMAS INGREDIENTES | C31: 11174
A32: 142188 | B32: INDUSTRIA DE BENEFICIAMENTO DE LEITE MAR | C32: 16000
A33: 737 | B33: JSANTOS EMPILHADEIRA DE CARGAS EIRELI ME | C33: 3375
A34: 28092026 | B34: LEANDRO RENATO BERTOLDO | C34: 866.22
A35: 12979 | B35: RODOVIARIO CORSO LTDA | C35: 12217.6
A36: 140602 | B36: SIM REDE DE POSTOS LTDA | C36: 275.66
A37: 3159 FT | B37: TRANSPORTES IRMAOS BOHRER LTDA | C37: 12217.16
A38: 272434 FT | B38: TURBO TRANSPORTES E LOGISTICA LTDA | C38: 12084.38
A39: 32354 | B39: UNIROL ROLAMENTOS RETENT. PECAS LTDA. | C39: 138
... A42: 28092026 | B42: WESLEN MACHADO | C42: 744.02
A43: Total | C43: =SUM(C28:C42) -> 149305.93
A45: =D3 -> 30/09 - Quarta-Feira
A46: 1037793 | B46: (sem nome) | C46: 400
A47: 1182491280 | B47: (sem nome) | C47: 764.1
A48: 1183692167 | B48: (sem nome) | C48: 363.6
A49: 1183697278 | B49: (sem nome) | C49: 361.91
A50: 16142 | B50: (sem nome) | C50: 466.29
A51: 16143 | B51: (sem nome) | C51: 1162.16
A52: 16144 | B52: (sem nome) | C52: 260.52
A53: 16145 | B53: (sem nome) | C53: 593.94
A54: 4119 | B54: (sem nome) | C54: 120
A55: 6 | B55: (sem nome) | C55: 2254.75
A56: 68659030001 FT | B56: ALFA TRANSPORTES ESPECIAIS LTDA | C56: 289.68
A57: 5 | B57: ALIEVI ADVOGADOS ASSOCIADOS | C57: 2254.75
... A77: 0439819000 FT | B77: TRD TRANSPORTE RODOVIARIO DALFAN LTDA | C77: 187.55
A78: Total | C78: =SUM(C46:C77) -> 62277.03
A80: =E3 -> 01/10 - Quinta-Feira
A81: 25 | B81: (sem nome) | C81: 4272
A82: 26 | B82: (sem nome) | C82: 3733.16
A83: 4007 | B83: (sem nome) | C83: 338.54
A84: 54 | B84: (sem nome) | C84: 1689
A85: 73 | B85: (sem nome) | C85: 3350
A86: 7599 | B86: (sem nome) | C86: 238.58
A87: 9595 | B87: (sem nome) | C87: 745.02
A88: 8303 | B88: ACQUATEC INDUSTRIA, COMERCIO E TRANSPORTES DE PRODUTOS QUIMI | C88: 7247.05
A89: 526 | B89: AMPAK INDUSTRIA E COMERCIO LTDA | C89: 22441.31
A90: 31 | B90: ASSMANN & BELMONTE LTDA | C90: 1570
A91: 8231 | B91: ASSOC RIOGR DE EMPR DE ASSIST TEC E EXTENSAO RURAL - EMATER | C91: 1925
A92: 2641 FT | B92: C.L.N. TRANSPORTES LTDA | C92: 5653
... A103: 0439837000 FT | B103: TRD TRANSPORTE RODOVIARIO DALFAN LTDA | C103: 9219.67
A104: Total | C104: =SUM(C81:C103) -> 92943.66
A106: =F3 -> 02/10 - Sexta-Feira
A107: 3 | B107: (sem nome) | C107: 2070
A108: 77912 | B108: (sem nome) | C108: 130.66
A109: 8271 | B109: (sem nome) | C109: 2410.24
A110: 136049 | B110: ALAC LABORATORIO ALAC LTDA | C110: 1812.17
A111: 48889 | B111: CASA LIMPA PROD. DE LIMPEZA LTDA | C111: 528.5
A112: 16478 FT | B112: COTRACAR COOP DE PREST DE SERV DE TRANSP | C112: 43158.71
A113: 2 | B113: DANIEL VOGT SOCIEDADE INDIVIDUAL DE ADVO | C113: 2070
A114: 80661 | B114: DUBAI INDUSTRIA E COMERCIO DE PRODUTOS ALIMENTICIOS LTDA | C114: 435
A115: 39 | B115: I. J. DRESCH LTDA | C115: 8000
A116: 44024 | B116: IND.DE PRODUTOS ALIMENTICIOS O.K. LTDA | C116: 725.7
A117: 167907 | B117: LOJAS FRICKE LTDA | C117: 319.97
A118: 84834 | B118: LUCIANA D. R. ARNHOLDO | C118: 240
... A126: 22249 | B126: VIDEIRA VERDE PROD ALIM EIRELI | C126: 4000
A127: Total | C127: =SUM(C107:C126) -> 77091.29
A129: IMPOSTOS
A130: =B4 -> 46293
A131: Total impostos | C131: 0
A133: =C4 -> 46294
A134: Total impostos | C134: 0
A136: =D4 -> 46295
A137: 14688 | B137: (sem nome) | C137: 12.5
A138: 7184 | B138: (sem nome) | C138: 15.2
A139: 1317 | B139: ISS RETIDO A RECOLHER | C139: 90.57
A140: Total impostos | C140: =SUM(C137:C139) -> 118.27
A142: =E4 -> 46296
A143: Total impostos | C143: 0
A145: =F4 -> 46297
A146: Total impostos | C146: 0

Sheet Config_Carteiras
A1: Carteira | B1: D+ | C1: Observação | E1: Edite o D+ aqui (ou as datas em Dias_Sem_Compensacao): Detalhamento e Planilha1 recalculam sozinhos. Carteira sem cadastro = D+1.
A2: 100 | B2: 1
A3: 33 | B3: 1
A4: 102 | B4: 0
A5: 74 | B5: 1

Sheet Dias_Sem_Compensacao
A1: Data | B1: Descrição

Sheet Detalhamento
A1: Data bruto | B1: Carteira | C1: Código | D1: Tipo | E1: D+ | F1: Cliente | G1: Entrada banco | H1: Fornecedor/A pagar | I1: Saída banco | J1: Fornecedor | K1: Duplicata
A2: 46287 | B2: BANRISUL COBRANCA | C2: 100 | D2: CLIENTES | E2: =IF(LEFT(D2,6)="CLIENT",IFERROR(VLOOKUP(C2,Config_Carteiras!$A:$B,2,FALSE),1),"") -> 1 | F2: 385 | G2: =IF(LEFT(D2,6)="CLIENT",IF(E2=0,WORKDAY(A2-1,1,Dias_Sem_Compensacao!$A$2:$A$500),WORKDAY(A2,E2,Dias_Sem_Compensacao!$A$2:$A$500)),"") -> 46288 | H2: 0 | I2: 46287 | J2: ADRIANA BEDINOTO GUERRA 01204028079 | K2: 220758
A3: 46287 | B3: BANRISUL COBRANCA | C3: 100 | D3: CLIENTES | E3: =IF(LEFT(D3,6)="CLIENT",IFERROR(VLOOKUP(C3,Config_Carteiras!$A:$B,2,FALSE),1),"") -> 1 | F3: 442.29 | G3: =IF(LEFT(D3,6)="CLIENT",IF(E3=0,WORKDAY(A3-1,1,Dias_Sem_Compensacao!$A$2:$A$500),WORKDAY(A3,E3,Dias_Sem_Compensacao!$A$2:$A$500)),"") -> 46288 | H3: 0 | I3: 46287 | J3: FABIO P LIXINSKI | K3: 221083
A4: 46287 | B4: BANRISUL COBRANCA | C4: 100 | D4: CLIENTES | E4: =IF(LEFT(D4,6)="CLIENT",IFERROR(VLOOKUP(C4,Config_Carteiras!$A:$B,2,FALSE),1),"") -> 1 | F4: 355.6 | G4: =IF(LEFT(D4,6)="CLIENT",IF(E4=0,WORKDAY(A4-1,1,Dias_Sem_Compensacao!$A$2:$A$500),WORKDAY(A4,E4,Dias_Sem_Compensacao!$A$2:$A$500)),"") -> 46288 | H4: 0 | I4: 46287 | J4: PABLO MARQUES DA FONTOURA CORREA 03101692083 | K4: 220504
A5: 46288 | B5: BANRISUL COBRANCA | C5: 100 | D5: CLIENTES | E5: =IF(LEFT(D5,6)="CLIENT",IFERROR(VLOOKUP(C5,Config_Carteiras!$A:$B,2,FALSE),1),"") -> 1 | F5: 1102 | G5: =IF(LEFT(D5,6)="CLIENT",IF(E5=0,WORKDAY(A5-1,1,Dias_Sem_Compensacao!$A$2:$A$500),WORKDAY(A5,E5,Dias_Sem_Compensacao!$A$2:$A$500)),"") -> 46289 | H5: 0 | I5: 46288 | J5: FABIO IRINEU NATIVIDADE PEREIRA | K5: 219988
A6: 46288 | B6: BANRISUL COBRANCA | C6: 100 | D6: CLIENTES | E6: =IF(LEFT(D6,6)="CLIENT",IFERROR(VLOOKUP(C6,Config_Carteiras!$A:$B,2,FALSE),1),"") -> 1 | F6: 1102 | G6: =IF(LEFT(D6,6)="CLIENT",IF(E6=0,WORKDAY(A6-1,1,Dias_Sem_Compensacao!$A$2:$A$500),WORKDAY(A6,E6,Dias_Sem_Compensacao!$A$2:$A$500)),"") -> 46289 | H6: 0 | I6: 46288 | K6: 220560
A7: 46288 | B7: BANRISUL COBRANCA | C7: 100 | D7: CLIENTES | E7: =IF(LEFT(D7,6)="CLIENT",IFERROR(VLOOKUP(C7,Config_Carteiras!$A:$B,2,FALSE),1),"") -> 1 | F7: 656 | G7: =IF(LEFT(D7,6)="CLIENT",IF(E7=0,WORKDAY(A7-1,1,Dias_Sem_Compensacao!$A$2:$A$500),WORKDAY(A7,E7,Dias_Sem_Compensacao!$A$2:$A$500)),"") -> 46289 | H7: 0 | I7: 46288 | J7: SUPERMERCADO TODO DIA LTDA | K7: 220353
A8: 46288 | B8: BANRISUL COBRANCA | C8: 100 | D8: CLIENTES | E8: =IF(LEFT(D8,6)="CLIENT",IFERROR(VLOOKUP(C8,Config_Carteiras!$A:$B,2,FALSE),1),"") -> 1 | F8: 420 | G8: =IF(LEFT(D8,6)="CLIENT",IF(E8=0,WORKDAY(A8-1,1,Dias_Sem_Compensacao!$A$2:$A$500),WORKDAY(A8,E8,Dias_Sem_Compensacao!$A$2:$A$500)),"") -> 46289 | H8: 0 | I8: 46288 | J8: THIARLA DA SILVA SILVEIRA | K8: 220608
A9: 46288 | B9: BANRISUL COBRANCA | C9: 100 | D9: CLIENTES | E9: =IF(LEFT(D9,6)="CLIENT",IFERROR(VLOOKUP(C9,Config_Carteiras!$A:$B,2,FALSE),1),"") -> 1 | F9: 364.96 | G9: =IF(LEFT(D9,6)="CLIENT",IF(E9=0,WORKDAY(A9-1,1,Dias_Sem_Compensacao!$A$2:$A$500),WORKDAY(A9,E9,Dias_Sem_Compensacao!$A$2:$A$500)),"") -> 46289 | H9: 0 | I9: 46288 | K9: 221170
A10: 46289 | B10: BANRISUL COBRANCA | C10: 100 | D10: CLIENTES | E10: =IF(LEFT(D10,6)="CLIENT",IFERROR(VLOOKUP(C10,Config_Carteiras!$A:$B,2,FALSE),1),"") -> 1 | F10: 671.5 | G10: =IF(LEFT(D10,6)="CLIENT",IF(E10=0,WORKDAY(A10-1,1,Dias_Sem_Compensacao!$A$2:$A$500),WORKDAY(A10,E10,Dias_Sem_Compensacao!$A$2:$A$500)),"") -> 46290 | H10: 0 | I10: 46289 | J10: COMERCIO DE ALIMENTOS SANTI LTDA | K10: 219683
A11: 46289 | B11: BANRISUL COBRANCA | C11: 100 | D11: CLIENTES | E11: =IF(LEFT(D11,6)="CLIENT",IFERROR(VLOOKUP(C11,Config_Carteiras!$A:$B,2,FALSE),1),"") -> 1 | F11: 660 | G11: =IF(LEFT(D11,6)="CLIENT",IF(E11=0,WORKDAY(A11-1,1,Dias_Sem_Compensacao!$A$2:$A$500),WORKDAY(A11,E11,Dias_Sem_Compensacao!$A$2:$A$500)),"") -> 46290 | H11: 0 | I11: 46289 | J11: ELZA CELANIRA ESTEVES DE MEDEIROS | K11: 220860
A12: 46290 | B12: BANRISUL COBRANCA | C12: 100 | D12: CLIENTES | E12: =IF(LEFT(D12,6)="CLIENT",IFERROR(VLOOKUP(C12,Config_Carteiras!$A:$B,2,FALSE),1),"") -> 1 | F12: 672 | G12: =IF(LEFT(D12,6)="CLIENT",IF(E12=0,WORKDAY(A12-1,1,Dias_Sem_Compensacao!$A$2:$A$500),WORKDAY(A12,E12,Dias_Sem_Compensacao!$A$2:$A$500)),"") -> 46293 | H12: 0 | I12: 46290 | J12: COMERCIO DE ALIMENTOS SANTI LTDA | K12: 220654
A13: 46293 | B13: BANRISUL COBRANCA | C13: 100 | D13: CLIENTES | E13: =IF(LEFT(D13,6)="CLIENT",IFERROR(VLOOKUP(C13,Config_Carteiras!$A:$B,2,FALSE),1),"") -> 1 | F13: 351.4 | G13: =IF(LEFT(D13,6)="CLIENT",IF(E13=0,WORKDAY(A13-1,1,Dias_Sem_Compensacao!$A$2:$A$500),WORKDAY(A13,E13,Dias_Sem_Compensacao!$A$2:$A$500)),"") -> 46294 | H13: 0 | I13: 46293 | J13: ANTONIO KRAHL TERRA | K13: 221270
A14: 46293 | B14: BANRISUL COBRANCA | C14: 100 | D14: CLIENTES | E14: =IF(LEFT(D14,6)="CLIENT",IFERROR(VLOOKUP(C14,Config_Carteiras!$A:$B,2,FALSE),1),"") -> 1 | F14: 701.25 | G14: =IF(LEFT(D14,6)="CLIENT",IF(E14=0,WORKDAY(A14-1,1,Dias_Sem_Compensacao!$A$2:$A$500),WORKDAY(A14,E14,Dias_Sem_Compensacao!$A$2:$A$500)),"") -> 46294 | H14: 0 | I14: 46293 | J14: COMERCIO E TRANSPORTE DE FRUTAS JUSTO LTDA | K14: 220429
A15: 46293 | B15: BANRISUL COBRANCA | C15: 100 | D15: CLIENTES | E15: =IF(LEFT(D15,6)="CLIENT",IFERROR(VLOOKUP(C15,Config_Carteiras!$A:$B,2,FALSE),1),"") -> 1 | F15: 406 | G15: =IF(LEFT(D15,6)="CLIENT",IF(E15=0,WORKDAY(A15-1,1,Dias_Sem_Compensacao!$A$2:$A$500),WORKDAY(A15,E15,Dias_Sem_Compensacao!$A$2:$A$500)),"") -> 46294 | H15: 0 | I15: 46293 | J15: CRISTIANO DA SILVA DE AVILA | K15: 220947
A16: 46293 | B16: BANRISUL COBRANCA | C16: 100 | D16: CLIENTES | E16: =IF(LEFT(D16,6)="CLIENT",IFERROR(VLOOKUP(C16,Config_Carteiras!$A:$B,2,FALSE),1),"") -> 1 | F16: 586 | G16: =IF(LEFT(D16,6)="CLIENT",IF(E16=0,WORKDAY(A16-1,1,Dias_Sem_Compensacao!$A$2:$A$500),WORKDAY(A16,E16,Dias_Sem_Compensacao!$A$2:$A$500)),"") -> 46294 | H16: 0 | I16: 46293 | J16: DS ATACADO E DISTRIBUICAO DE DOCES E SALGADOS LTDA. | K16: 220430
A17: 46293 | B17: BANRISUL COBRANCA | C17: 100 | D17: CLIENTES | E17: =IF(LEFT(D17,6)="CLIENT",IFERROR(VLOOKUP(C17,Config_Carteiras!$A:$B,2,FALSE),1),"") -> 1 | F17: 1243 | G17: =IF(LEFT(D17,6)="CLIENT",IF(E17=0,WORKDAY(A17-1,1,Dias_Sem_Compensacao!$A$2:$A$500),WORKDAY(A17,E17,Dias_Sem_Compensacao!$A$2:$A$500)),"") -> 46294 | H17: 0 | I17: 46293 | J17: ERICK HUBER CABREIRA | K17: 220958
A18: 46293 | B18: BANRISUL COBRANCA | C18: 100 | D18: CLIENTES | E18: =IF(LEFT(D18,6)="CLIENT",IFERROR(VLOOKUP(C18,Config_Carteiras!$A:$B,2,FALSE),1),"") -> 1 | F18: 3321 | G18: =IF(LEFT(D18,6)="CLIENT",IF(E18=0,WORKDAY(A18-1,1,Dias_Sem_Compensacao!$A$2:$A$500),WORKDAY(A18,E18,Dias_Sem_Compensacao!$A$2:$A$500)),"") -> 46294 | H18: 0 | I18: 46293 | J18: NICARETTA IRMAOS LTDA | K18: 220173
A19: 46293 | B19: BANRISUL COBRANCA | C19: 100 | D19: CLIENTES | E19: =IF(LEFT(D19,6)="CLIENT",IFERROR(VLOOKUP(C19,Config_Carteiras!$A:$B,2,FALSE),1),"") -> 1 | F19: 326 | G19: =IF(LEFT(D19,6)="CLIENT",IF(E19=0,WORKDAY(A19-1,1,Dias_Sem_Compensacao!$A$2:$A$500),WORKDAY(A19,E19,Dias_Sem_Compensacao!$A$2:$A$500)),"") -> 46294 | H19: 0 | I19: 46293 | J19: RESTAURANTE E PADARIA KICOLOSSO LTDA | K19: 220935
A20: 46293 | B20: BANRISUL COBRANCA | C20: 100 | D20: CLIENTES | E20: =IF(LEFT(D20,6)="CLIENT",IFERROR(VLOOKUP(C20,Config_Carteiras!$A:$B,2,FALSE),1),"") -> 1 | F20: 390.6 | G20: =IF(LEFT(D20,6)="CLIENT",IF(E20=0,WORKDAY(A20-1,1,Dias_Sem_Compensacao!$A$2:$A$500),WORKDAY(A20,E20,Dias_Sem_Compensacao!$A$2:$A$500)),"") -> 46294 | H20: 0 | I20: 46293 | J20: RUKART GUILHERME JOST | K20: 221286
A21: 46294 | B21: BANRISUL COBRANCA | C21: 100 | D21: CLIENTES | E21: =IF(LEFT(D21,6)="CLIENT",IFERROR(VLOOKUP(C21,Config_Carteiras!$A:$B,2,FALSE),1),"") -> 1 | F21: 385 | G21: =IF(LEFT(D21,6)="CLIENT",IF(E21=0,WORKDAY(A21-1,1,Dias_Sem_Compensacao!$A$2:$A$500),WORKDAY(A21,E21,Dias_Sem_Compensacao!$A$2:$A$500)),"") -> 46295 | H21: 0 | I21: 46294 | J21: ADRIANA BEDINOTO GUERRA 01204028079 | K21: 220758
... A32: 46294 | B32: BANRISUL COBRANCA | C32: 100 | D32: CLIENTES | E32: =IF(LEFT(D32,6)="CLIENT",IFERROR(VLOOKUP(C32,Config_Carteiras!$A:$B,2,FALSE),1),"") -> 1 | F32: 627.3 | G32: =IF(LEFT(D32,6)="CLIENT",IF(E32=0,WORKDAY(A32-1,1,Dias_Sem_Compensacao!$A$2:$A$500),WORKDAY(A32,E32,Dias_Sem_Compensacao!$A$2:$A$500)),"") -> 46295 | H32: 0 | I32: 46294 | J32: COMERCIO DE ALIMENTOS ROHENKHOL LTDA. | K32: 220679
A33: 46294 | B33: BANRISUL COBRANCA | C33: 100 | D33: CLIENTES | E33: =IF(LEFT(D33,6)="CLIENT",IFERROR(VLOOKUP(C33,Config_Carteiras!$A:$B,2,FALSE),1),"") -> 1 | F33: 1542 | G33: =IF(LEFT(D33,6)="CLIENT",IF(E33=0,WORKDAY(A33-1,1,Dias_Sem_Compensacao!$A$2:$A$500),WORKDAY(A33,E33,Dias_Sem_Compensacao!$A$2:$A$500)),"") -> 46295 | H33: 0 | I33: 46294 | K33: 220684
A34: 46294 | B34: BANRISUL COBRANCA | C34: 100 | D34: CLIENTES | E34: =IF(LEFT(D34,6)="CLIENT",IFERROR(VLOOKUP(C34,Config_Carteiras!$A:$B,2,FALSE),1),"") -> 1 | F34: 1524 | G34: =IF(LEFT(D34,6)="CLIENT",IF(E34=0,WORKDAY(A34-1,1,Dias_Sem_Compensacao!$A$2:$A$500),WORKDAY(A34,E34,Dias_Sem_Compensacao!$A$2:$A$500)),"") -> 46295 | H34: 0 | I34: 46294 | J34: COOPERATIVA AGRÁRIA SAO JOSE LTDA. | K34: 220768
A35: 46294 | B35: BANRISUL COBRANCA | C35: 100 | D35: CLIENTES | E35: =IF(LEFT(D35,6)="CLIENT",IFERROR(VLOOKUP(C35,Config_Carteiras!$A:$B,2,FALSE),1),"") -> 1 | F35: 1523.2 | G35: =IF(LEFT(D35,6)="CLIENT",IF(E35=0,WORKDAY(A35-1,1,Dias_Sem_Compensacao!$A$2:$A$500),WORKDAY(A35,E35,Dias_Sem_Compensacao!$A$2:$A$500)),"") -> 46295 | H35: 0 | I35: 46294 | J35: COOPERATIVA DOS PRODUTORES DE ALECRIM LTDA. | K35: 220687
A36: 46294 | B36: BANRISUL COBRANCA | C36: 100 | D36: CLIENTES | E36: =IF(LEFT(D36,6)="CLIENT",IFERROR(VLOOKUP(C36,Config_Carteiras!$A:$B,2,FALSE),1),"") -> 1 | F36: 577.05 | G36: =IF(LEFT(D36,6)="CLIENT",IF(E36=0,WORKDAY(A36-1,1,Dias_Sem_Compensacao!$A$2:$A$500),WORKDAY(A36,E36,Dias_Sem_Compensacao!$A$2:$A$500)),"") -> 46295 | H36: 0 | I36: 46294 | J36: DESEJOS DO PALADAR LTDA | K36: 221079
A37: 46294 | B37: BANRISUL COBRANCA | C37: 100 | D37: CLIENTES | E37: =IF(LEFT(D37,6)="CLIENT",IFERROR(VLOOKUP(C37,Config_Carteiras!$A:$B,2,FALSE),1),"") -> 1 | F37: 377.7 | G37: =IF(LEFT(D37,6)="CLIENT",IF(E37=0,WORKDAY(A37-1,1,Dias_Sem_Compensacao!$A$2:$A$500),WORKDAY(A37,E37,Dias_Sem_Compensacao!$A$2:$A$500)),"") -> 46295 | H37: 0 | I37: 46294 | J37: DIEGO ANDREI ROHTE | K37: 220480
A38: 46294 | B38: BANRISUL COBRANCA | C38: 100 | D38: CLIENTES | E38: =IF(LEFT(D38,6)="CLIENT",IFERROR(VLOOKUP(C38,Config_Carteiras!$A:$B,2,FALSE),1),"") -> 1 | F38: 1051 | G38: =IF(LEFT(D38,6)="CLIENT",IF(E38=0,WORKDAY(A38-1,1,Dias_Sem_Compensacao!$A$2:$A$500),WORKDAY(A38,E38,Dias_Sem_Compensacao!$A$2:$A$500)),"") -> 46295 | H38: 0 | I38: 46294 | J38: DU-PAO INDUSTRIA E COMERCIO DE PAES LTDA. | K38: 220215
A39: 46294 | B39: BANRISUL COBRANCA | C39: 100 | D39: CLIENTES | E39: =IF(LEFT(D39,6)="CLIENT",IFERROR(VLOOKUP(C39,Config_Carteiras!$A:$B,2,FALSE),1),"") -> 1 | F39: 789.2 | G39: =IF(LEFT(D39,6)="CLIENT",IF(E39=0,WORKDAY(A39-1,1,Dias_Sem_Compensacao!$A$2:$A$500),WORKDAY(A39,E39,Dias_Sem_Compensacao!$A$2:$A$500)),"") -> 46295 | H39: 0 | I39: 46294 | J39: EDER CENAIR PEREIRA | K39: 220692
A40: 46294 | B40: BANRISUL COBRANCA | C40: 100 | D40: CLIENTES | E40: =IF(LEFT(D40,6)="CLIENT",IFERROR(VLOOKUP(C40,Config_Carteiras!$A:$B,2,FALSE),1),"") -> 1 | F40: 366.6 | G40: =IF(LEFT(D40,6)="CLIENT",IF(E40=0,WORKDAY(A40-1,1,Dias_Sem_Compensacao!$A$2:$A$500),WORKDAY(A40,E40,Dias_Sem_Compensacao!$A$2:$A$500)),"") -> 46295 | H40: 0 | I40: 46294 | J40: ELAINE MARIA LENZ | K40: 220695
A41: 46294 | B41: BANRISUL COBRANCA | C41: 100 | D41: CLIENTES | E41: =IF(LEFT(D41,6)="CLIENT",IFERROR(VLOOKUP(C41,Config_Carteiras!$A:$B,2,FALSE),1),"") -> 1 | F41: 1082 | G41: =IF(LEFT(D41,6)="CLIENT",IF(E41=0,WORKDAY(A41-1,1,Dias_Sem_Compensacao!$A$2:$A$500),WORKDAY(A41,E41,Dias_Sem_Compensacao!$A$2:$A$500)),"") -> 46295 | H41: 0 | I41: 46294 | J41: ELIO SEBASTIAO RAUPP | K41: 220211
A42: 46294 | B42: BANRISUL COBRANCA | C42: 100 | D42: CLIENTES | E42: =IF(LEFT(D42,6)="CLIENT",IFERROR(VLOOKUP(C42,Config_Carteiras!$A:$B,2,FALSE),1),"") -> 1 | F42: 656 | G42: =IF(LEFT(D42,6)="CLIENT",IF(E42=0,WORKDAY(A42-1,1,Dias_Sem_Compensacao!$A$2:$A$500),WORKDAY(A42,E42,Dias_Sem_Compensacao!$A$2:$A$500)),"") -> 46295 | H42: 0 | I42: 46294 | J42: ELISANGELA TEREZINHA ANDRADE BATISTA | K42: 220763
A43: 46294 | B43: BANRISUL COBRANCA | C43: 100 | D43: CLIENTES | E43: =IF(LEFT(D43,6)="CLIENT",IFERROR(VLOOKUP(C43,Config_Carteiras!$A:$B,2,FALSE),1),"") -> 1 | F43: 914.7 | G43: =IF(LEFT(D43,6)="CLIENT",IF(E43=0,WORKDAY(A43-1,1,Dias_Sem_Compensacao!$A$2:$A$500),WORKDAY(A43,E43,Dias_Sem_Compensacao!$A$2:$A$500)),"") -> 46295 | H43: 0 | I43: 46294 | J43: ELTON KRONBAUER LTDA | K43: 220483
A44: 46294 | B44: BANRISUL COBRANCA | C44: 100 | D44: CLIENTES | E44: =IF(LEFT(D44,6)="CLIENT",IFERROR(VLOOKUP(C44,Config_Carteiras!$A:$B,2,FALSE),1),"") -> 1 | F44: 484.2 | G44: =IF(LEFT(D44,6)="CLIENT",IF(E44=0,WORKDAY(A44-1,1,Dias_Sem_Compensacao!$A$2:$A$500),WORKDAY(A44,E44,Dias_Sem_Compensacao!$A$2:$A$500)),"") -> 46295 | H44: 0 | I44: 46294 | J44: ENIO LUIZ STANGHERLIN | K44: 220757
A45: 46294 | B45: BANRISUL COBRANCA | C45: 100 | D45: CLIENTES | E45: =IF(LEFT(D45,6)="CLIENT",IFERROR(VLOOKUP(C45,Config_Carteiras!$A:$B,2,FALSE),1),"") -> 1 | F45: 578 | G45: =IF(LEFT(D45,6)="CLIENT",IF(E45=0,WORKDAY(A45-1,1,Dias_Sem_Compensacao!$A$2:$A$500),WORKDAY(A45,E45,Dias_Sem_Compensacao!$A$2:$A$500)),"") -> 46295 | H45: 0 | I45: 46294 | J45: EUCLEIA MARTINELLI 98760181087 | K45: 221045
... A78: 46294 | B78: BANRISUL COBRANCA | C78: 100 | D78: CLIENTES | E78: =IF(LEFT(D78,6)="CLIENT",IFERROR(VLOOKUP(C78,Config_Carteiras!$A:$B,2,FALSE),1),"") -> 1 | F78: 7503 | G78: =IF(LEFT(D78,6)="CLIENT",IF(E78=0,WORKDAY(A78-1,1,Dias_Sem_Compensacao!$A$2:$A$500),WORKDAY(A78,E78,Dias_Sem_Compensacao!$A$2:$A$500)),"") -> 46295 | H78: 0 | I78: 46294 | J78: SILVA ATACAREJO LTDA | K78: 220496
A79: 46294 | B79: BANRISUL COBRANCA | C79: 100 | D79: CLIENTES | E79: =IF(LEFT(D79,6)="CLIENT",IFERROR(VLOOKUP(C79,Config_Carteiras!$A:$B,2,FALSE),1),"") -> 1 | F79: 5306 | G79: =IF(LEFT(D79,6)="CLIENT",IF(E79=0,WORKDAY(A79-1,1,Dias_Sem_Compensacao!$A$2:$A$500),WORKDAY(A79,E79,Dias_Sem_Compensacao!$A$2:$A$500)),"") -> 46295 | H79: 0 | I79: 46294 | K79: 220677
A80: 46294 | B80: BANRISUL COBRANCA | C80: 100 | D80: CLIENTES | E80: =IF(LEFT(D80,6)="CLIENT",IFERROR(VLOOKUP(C80,Config_Carteiras!$A:$B,2,FALSE),1),"") -> 1 | F80: 3224 | G80: =IF(LEFT(D80,6)="CLIENT",IF(E80=0,WORKDAY(A80-1,1,Dias_Sem_Compensacao!$A$2:$A$500),WORKDAY(A80,E80,Dias_Sem_Compensacao!$A$2:$A$500)),"") -> 46295 | H80: 0 | I80: 46294 | K80: 220678
A81: 46294 | B81: BANRISUL COBRANCA | C81: 100 | D81: CLIENTES | E81: =IF(LEFT(D81,6)="CLIENT",IFERROR(VLOOKUP(C81,Config_Carteiras!$A:$B,2,FALSE),1),"") -> 1 | F81: 386 | G81: =IF(LEFT(D81,6)="CLIENT",IF(E81=0,WORKDAY(A81-1,1,Dias_Sem_Compensacao!$A$2:$A$500),WORKDAY(A81,E81,Dias_Sem_Compensacao!$A$2:$A$500)),"") -> 46295 | H81: 0 | I81: 46294 | J81: SILVEIRA BITENCOURT PADARIA E CONFEITARIA LTDA | K81: 220753
A82: 46294 | B82: BANRISUL COBRANCA | C82: 100 | D82: CLIENTES | E82: =IF(LEFT(D82,6)="CLIENT",IFERROR(VLOOKUP(C82,Config_Carteiras!$A:$B,2,FALSE),1),"") -> 1 | F82: 484 | G82: =IF(LEFT(D82,6)="CLIENT",IF(E82=0,WORKDAY(A82-1,1,Dias_Sem_Compensacao!$A$2:$A$500),WORKDAY(A82,E82,Dias_Sem_Compensacao!$A$2:$A$500)),"") -> 46295 | H82: 0 | I82: 46294 | J82: SONIA TEREZINHA SANTOS DOS SANTOS | K82: 221082
A83: 46294 | B83: BANRISUL COBRANCA | C83: 100 | D83: CLIENTES | E83: =IF(LEFT(D83,6)="CLIENT",IFERROR(VLOOKUP(C83,Config_Carteiras!$A:$B,2,FALSE),1),"") -> 1 | F83: 307.56 | G83: =IF(LEFT(D83,6)="CLIENT",IF(E83=0,WORKDAY(A83-1,1,Dias_Sem_Compensacao!$A$2:$A$500),WORKDAY(A83,E83,Dias_Sem_Compensacao!$A$2:$A$500)),"") -> 46295 | H83: 0 | I83: 46294 | J83: SUPERMERCADO SUPER SANTO ANTONIO LTDA | K83: 220784
A84: 46294 | B84: BANRISUL COBRANCA | C84: 100 | D84: CLIENTES | E84: =IF(LEFT(D84,6)="CLIENT",IFERROR(VLOOKUP(C84,Config_Carteiras!$A:$B,2,FALSE),1),"") -> 1 | F84: 871 | G84: =IF(LEFT(D84,6)="CLIENT",IF(E84=0,WORKDAY(A84-1,1,Dias_Sem_Compensacao!$A$2:$A$500),WORKDAY(A84,E84,Dias_Sem_Compensacao!$A$2:$A$500)),"") -> 46295 | H84: 0 | I84: 46294 | J84: WALDIR ANTONIO BOHN | K84: 220188
A85: 46295 | B85: BANRISUL COBRANCA | C85: 100 | D85: CLIENTES | E85: =IF(LEFT(D85,6)="CLIENT",IFERROR(VLOOKUP(C85,Config_Carteiras!$A:$B,2,FALSE),1),"") -> 1 | F85: 435 | G85: =IF(LEFT(D85,6)="CLIENT",IF(E85=0,WORKDAY(A85-1,1,Dias_Sem_Compensacao!$A$2:$A$500),WORKDAY(A85,E85,Dias_Sem_Compensacao!$A$2:$A$500)),"") -> 46296 | H85: 0 | I85: 46295 | J85: ADRIANA SANCHEZ ZULIANE | K85: 220589
A86: 46295 | B86: BANRISUL COBRANCA | C86: 100 | D86: CLIENTES | E86: =IF(LEFT(D86,6)="CLIENT",IFERROR(VLOOKUP(C86,Config_Carteiras!$A:$B,2,FALSE),1),"") -> 1 | F86: 378 | G86: =IF(LEFT(D86,6)="CLIENT",IF(E86=0,WORKDAY(A86-1,1,Dias_Sem_Compensacao!$A$2:$A$500),WORKDAY(A86,E86,Dias_Sem_Compensacao!$A$2:$A$500)),"") -> 46296 | H86: 0 | I86: 46295 | J86: ALEX RODRIGUES 02314211090 | K86: 220552
A87: 46295 | B87: BANRISUL COBRANCA | C87: 100 | D87: CLIENTES | E87: =IF(LEFT(D87,6)="CLIENT",IFERROR(VLOOKUP(C87,Config_Carteiras!$A:$B,2,FALSE),1),"") -> 1 | F87: 1370.88 | G87: =IF(LEFT(D87,6)="CLIENT",IF(E87=0,WORKDAY(A87-1,1,Dias_Sem_Compensacao!$A$2:$A$500),WORKDAY(A87,E87,Dias_Sem_Compensacao!$A$2:$A$500)),"") -> 46296 | H87: 0 | I87: 46295 | J87: ANTONIO JAMIR GUTERRES SOARES 70076189015 | K87: 220556
A88: 46295 | B88: BANRISUL COBRANCA | C88: 100 | D88: CLIENTES | E88: =IF(LEFT(D88,6)="CLIENT",IFERROR(VLOOKUP(C88,Config_Carteiras!$A:$B,2,FALSE),1),"") -> 1 | F88: 675.5 | G88: =IF(LEFT(D88,6)="CLIENT",IF(E88=0,WORKDAY(A88-1,1,Dias_Sem_Compensacao!$A$2:$A$500),WORKDAY(A88,E88,Dias_Sem_Compensacao!$A$2:$A$500)),"") -> 46296 | H88: 0 | I88: 46295 | J88: AREND COMERCIO VAREJISTA MERCADORIAS ALIMENTICIAS LTDA | K88: 220613
A89: 46295 | B89: BANRISUL COBRANCA | C89: 100 | D89: CLIENTES | E89: =IF(LEFT(D89,6)="CLIENT",IFERROR(VLOOKUP(C89,Config_Carteiras!$A:$B,2,FALSE),1),"") -> 1 | F89: 6120 | G89: =IF(LEFT(D89,6)="CLIENT",IF(E89=0,WORKDAY(A89-1,1,Dias_Sem_Compensacao!$A$2:$A$500),WORKDAY(A89,E89,Dias_Sem_Compensacao!$A$2:$A$500)),"") -> 46296 | H89: 0 | I89: 46295 | J89: BALBINOT & CIA LTDA | K89: 220592
A90: 46295 | B90: BANRISUL COBRANCA | C90: 100 | D90: CLIENTES | E90: =IF(LEFT(D90,6)="CLIENT",IFERROR(VLOOKUP(C90,Config_Carteiras!$A:$B,2,FALSE),1),"") -> 1 | F90: 390.56 | G90: =IF(LEFT(D90,6)="CLIENT",IF(E90=0,WORKDAY(A90-1,1,Dias_Sem_Compensacao!$A$2:$A$500),WORKDAY(A90,E90,Dias_Sem_Compensacao!$A$2:$A$500)),"") -> 46296 | H90: 0 | I90: 46295 | J90: BERENICE GENEROSA DOS SANTOS | K90: 221426
A91: 46295 | B91: BANRISUL COBRANCA | C91: 100 | D91: CLIENTES | E91: =IF(LEFT(D91,6)="CLIENT",IFERROR(VLOOKUP(C91,Config_Carteiras!$A:$B,2,FALSE),1),"") -> 1 | F91: 2211 | G91: =IF(LEFT(D91,6)="CLIENT",IF(E91=0,WORKDAY(A91-1,1,Dias_Sem_Compensacao!$A$2:$A$500),WORKDAY(A91,E91,Dias_Sem_Compensacao!$A$2:$A$500)),"") -> 46296 | H91: 0 | I91: 46295 | J91: CARDOSO, RITERBUSCH E CIA LTDA. | K91: 220538
A92: 46295 | B92: BANRISUL COBRANCA | C92: 100 | D92: CLIENTES | E92: =IF(LEFT(D92,6)="CLIENT",IFERROR(VLOOKUP(C92,Config_Carteiras!$A:$B,2,FALSE),1),"") -> 1 | F92: 2321 | G92: =IF(LEFT(D92,6)="CLIENT",IF(E92=0,WORKDAY(A92-1,1,Dias_Sem_Compensacao!$A$2:$A$500),WORKDAY(A92,E92,Dias_Sem_Compensacao!$A$2:$A$500)),"") -> 46296 | H92: 0 | I92: 46295 | J92: CARLOS ALBERTO DOS SANTOS DUARTE | K92: 220596
A93: 46295 | B93: BANRISUL COBRANCA | C93: 100 | D93: CLIENTES | E93: =IF(LEFT(D93,6)="CLIENT",IFERROR(VLOOKUP(C93,Config_Carteiras!$A:$B,2,FALSE),1),"") -> 1 | F93: 735.5 | G93: =IF(LEFT(D93,6)="CLIENT",IF(E93=0,WORKDAY(A93-1,1,Dias_Sem_Compensacao!$A$2:$A$500),WORKDAY(A93,E93,Dias_Sem_Compensacao!$A$2:$A$500)),"") -> 46296 | H93: 0 | I93: 46295 | J93: CIANE DE SOUZA JARDIM LTDA. | K93: 220578
A94: 46295 | B94: BANRISUL COBRANCA | C94: 100 | D94: CLIENTES | E94: =IF(LEFT(D94,6)="CLIENT",IFERROR(VLOOKUP(C94,Config_Carteiras!$A:$B,2,FALSE),1),"") -> 1 | F94: 658 | G94: =IF(LEFT(D94,6)="CLIENT",IF(E94=0,WORKDAY(A94-1,1,Dias_Sem_Compensacao!$A$2:$A$500),WORKDAY(A94,E94,Dias_Sem_Compensacao!$A$2:$A$500)),"") -> 46296 | H94: 0 | I94: 46295 | K94: 221115
A95: 46295 | B95: BANRISUL COBRANCA | C95: 100 | D95: CLIENTES | E95: =IF(LEFT(D95,6)="CLIENT",IFERROR(VLOOKUP(C95,Config_Carteiras!$A:$B,2,FALSE),1),"") -> 1 | F95: 429 | G95: =IF(LEFT(D95,6)="CLIENT",IF(E95=0,WORKDAY(A95-1,1,Dias_Sem_Compensacao!$A$2:$A$500),WORKDAY(A95,E95,Dias_Sem_Compensacao!$A$2:$A$500)),"") -> 46296 | H95: 0 | I95: 46295 | J95: COMERCIO DE ALIMENTOS LIMA LTDA | K95: 220540
A96: 46295 | B96: BANRISUL COBRANCA | C96: 100 | D96: CLIENTES | E96: =IF(LEFT(D96,6)="CLIENT",IFERROR(VLOOKUP(C96,Config_Carteiras!$A:$B,2,FALSE),1),"") -> 1 | F96: 6090 | G96: =IF(LEFT(D96,6)="CLIENT",IF(E96=0,WORKDAY(A96-1,1,Dias_Sem_Compensacao!$A$2:$A$500),WORKDAY(A96,E96,Dias_Sem_Compensacao!$A$2:$A$500)),"") -> 46296 | H96: 0 | I96: 46295 | J96: COOPERATIVA AGRICOLA MISTA AGUDO LTDA. | K96: 220829
A97: 46295 | B97: BANRISUL COBRANCA | C97: 100 | D97: CLIENTES | E97: =IF(LEFT(D97,6)="CLIENT",IFERROR(VLOOKUP(C97,Config_Carteiras!$A:$B,2,FALSE),1),"") -> 1 | F97: 3656 | G97: =IF(LEFT(D97,6)="CLIENT",IF(E97=0,WORKDAY(A97-1,1,Dias_Sem_Compensacao!$A$2:$A$500),WORKDAY(A97,E97,Dias_Sem_Compensacao!$A$2:$A$500)),"") -> 46296 | H97: 0 | I97: 46295 | K97: 220830
A98: 46295 | B98: BANRISUL COBRANCA | C98: 100 | D98: CLIENTES | E98: =IF(LEFT(D98,6)="CLIENT",IFERROR(VLOOKUP(C98,Config_Carteiras!$A:$B,2,FALSE),1),"") -> 1 | F98: 1512 | G98: =IF(LEFT(D98,6)="CLIENT",IF(E98=0,WORKDAY(A98-1,1,Dias_Sem_Compensacao!$A$2:$A$500),WORKDAY(A98,E98,Dias_Sem_Compensacao!$A$2:$A$500)),"") -> 46296 | H98: 0 | I98: 46295 | J98: DIEGO CARDOSO | K98: 220314
A99: 46295 | B99: BANRISUL COBRANCA | C99: 100 | D99: CLIENTES | E99: =IF(LEFT(D99,6)="CLIENT",IFERROR(VLOOKUP(C99,Config_Carteiras!$A:$B,2,FALSE),1),"") -> 1 | F99: 257.85 | G99: =IF(LEFT(D99,6)="CLIENT",IF(E99=0,WORKDAY(A99-1,1,Dias_Sem_Compensacao!$A$2:$A$500),WORKDAY(A99,E99,Dias_Sem_Compensacao!$A$2:$A$500)),"") -> 46296 | H99: 0 | I99: 46295 | J99: DIVINO SABOR PADARIA E CONFEITARIA LTDA | K99: 220799
A100: 46295 | B100: BANRISUL COBRANCA | C100: 100 | D100: CLIENTES | E100: =IF(LEFT(D100,6)="CLIENT",IFERROR(VLOOKUP(C100,Config_Carteiras!$A:$B,2,FALSE),1),"") -> 1 | F100: 761 | G100: =IF(LEFT(D100,6)="CLIENT",IF(E100=0,WORKDAY(A100-1,1,Dias_Sem_Compensacao!$A$2:$A$500),WORKDAY(A100,E100,Dias_Sem_Compensacao!$A$2:$A$500)),"") -> 46296 | H100: 0 | I100: 46295 | J100: DOIS ZE INDUSTRIA DE PANIFICACAO LTDA. | K100: 220809
A101: 46295 | B101: BANRISUL COBRANCA | C101: 100 | D101: CLIENTES | E101: =IF(LEFT(D101,6)="CLIENT",IFERROR(VLOOKUP(C101,Config_Carteiras!$A:$B,2,FALSE),1),"") -> 1 | F101: 1050 | G101: =IF(LEFT(D101,6)="CLIENT",IF(E101=0,WORKDAY(A101-1,1,Dias_Sem_Compensacao!$A$2:$A$500),WORKDAY(A101,E101,Dias_Sem_Compensacao!$A$2:$A$500)),"") -> 46296 | H101: 0 | I101: 46295 | J101: EDUARDO ANTONIO DE LIMA CARRE 02741135037 | K101: 220539
A102: 46295 | B102: BANRISUL COBRANCA | C102: 100 | D102: CLIENTES | E102: =IF(LEFT(D102,6)="CLIENT",IFERROR(VLOOKUP(C102,Config_Carteiras!$A:$B,2,FALSE),1),"") -> 1 | F102: 1530 | G102: =IF(LEFT(D102,6)="CLIENT",IF(E102=0,WORKDAY(A102-1,1,Dias_Sem_Compensacao!$A$2:$A$500),WORKDAY(A102,E102,Dias_Sem_Compensacao!$A$2:$A$500)),"") -> 46296 | H102: 0 | I102: 46295 | J102: EDUARDO TATSCH | K102: 221162
A103: 46295 | B103: BANRISUL COBRANCA | C103: 100 | D103: CLIENTES | E103: =IF(LEFT(D103,6)="CLIENT",IFERROR(VLOOKUP(C103,Config_Carteiras!$A:$B,2,FALSE),1),"") -> 1 | F103: 1099.56 | G103: =IF(LEFT(D103,6)="CLIENT",IF(E103=0,WORKDAY(A103-1,1,Dias_Sem_Compensacao!$A$2:$A$500),WORKDAY(A103,E103,Dias_Sem_Compensacao!$A$2:$A$500)),"") -> 46296 | H103: 0 | I103: 46295 | J103: EVERTON LUIS FERNANDES ALBUQUERQUE | K103: 221431
A104: 46295 | B104: BANRISUL COBRANCA | C104: 100 | D104: CLIENTES | E104: =IF(LEFT(D104,6)="CLIENT",IFERROR(VLOOKUP(C104,Config_Carteiras!$A:$B,2,FALSE),1),"") -> 1 | F104: 1104 | G104: =IF(LEFT(D104,6)="CLIENT",IF(E104=0,WORKDAY(A104-1,1,Dias_Sem_Compensacao!$A$2:$A$500),WORKDAY(A104,E104,Dias_Sem_Compensacao!$A$2:$A$500)),"") -> 46296 | H104: 0 | I104: 46295 | J104: FABIO IRINEU NATIVIDADE PEREIRA | K104: 219988
A105: 46295 | B105: BANRISUL COBRANCA | C105: 100 | D105: CLIENTES | E105: =IF(LEFT(D105,6)="CLIENT",IFERROR(VLOOKUP(C105,Config_Carteiras!$A:$B,2,FALSE),1),"") -> 1 | F105: 1102 | G105: =IF(LEFT(D105,6)="CLIENT",IF(E105=0,WORKDAY(A105-1,1,Dias_Sem_Compensacao!$A$2:$A$500),WORKDAY(A105,E105,Dias_Sem_Compensacao!$A$2:$A$500)),"") -> 46296 | H105: 0 | I105: 46295 | K105: 220560
A106: 46295 | B106: BANRISUL COBRANCA | C106: 100 | D106: CLIENTES | E106: =IF(LEFT(D106,6)="CLIENT",IFERROR(VLOOKUP(C106,Config_Carteiras!$A:$B,2,FALSE),1),"") -> 1 | F106: 1574.37 | G106: =IF(LEFT(D106,6)="CLIENT",IF(E106=0,WORKDAY(A106-1,1,Dias_Sem_Compensacao!$A$2:$A$500),WORKDAY(A106,E106,Dias_Sem_Compensacao!$A$2:$A$500)),"") -> 46296 | H106: 0 | I106: 46295 | J106: FRANCIELE SOARES RODRIGUES | K106: 220332
A107: 46295 | B107: BANRISUL COBRANCA | C107: 100 | D107: CLIENTES | E107: =IF(LEFT(D107,6)="CLIENT",IFERROR(VLOOKUP(C107,Config_Carteiras!$A:$B,2,FALSE),1),"") -> 1 | F107: 357.5 | G107: =IF(LEFT(D107,6)="CLIENT",IF(E107=0,WORKDAY(A107-1,1,Dias_Sem_Compensacao!$A$2:$A$500),WORKDAY(A107,E107,Dias_Sem_Compensacao!$A$2:$A$500)),"") -> 46296 | H107: 0 | I107: 46295 | J107: FRANCISCO HELDER VILAGRAN DA ROSA | K107: 220825
A108: 46295 | B108: BANRISUL COBRANCA | C108: 100 | D108: CLIENTES | E108: =IF(LEFT(D108,6)="CLIENT",IFERROR(VLOOKUP(C108,Config_Carteiras!$A:$B,2,FALSE),1),"") -> 1 | F108: 787 | G108: =IF(LEFT(D108,6)="CLIENT",IF(E108=0,WORKDAY(A108-1,1,Dias_Sem_Compensacao!$A$2:$A$500),WORKDAY(A108,E108,Dias_Sem_Compensacao!$A$2:$A$500)),"") -> 46296 | H108: 0 | I108: 46295 | J108: FRUTEIRA REI DAS FRUTAS LTDA | K108: 219963
A109: 46295 | B109: BANRISUL COBRANCA | C109: 100 | D109: CLIENTES | E109: =IF(LEFT(D109,6)="CLIENT",IFERROR(VLOOKUP(C109,Config_Carteiras!$A:$B,2,FALSE),1),"") -> 1 | F109: 371.3 | G109: =IF(LEFT(D109,6)="CLIENT",IF(E109=0,WORKDAY(A109-1,1,Dias_Sem_Compensacao!$A$2:$A$500),WORKDAY(A109,E109,Dias_Sem_Compensacao!$A$2:$A$500)),"") -> 46296 | H109: 0 | I109: 46295 | J109: GABRIELA DA SILVA BRUM | K109: 221176
A110: 46295 | B110: BANRISUL COBRANCA | C110: 100 | D110: CLIENTES | E110: =IF(LEFT(D110,6)="CLIENT",IFERROR(VLOOKUP(C110,Config_Carteiras!$A:$B,2,FALSE),1),"") -> 1 | F110: 1099.89 | G110: =IF(LEFT(D110,6)="CLIENT",IF(E110=0,WORKDAY(A110-1,1,Dias_Sem_Compensacao!$A$2:$A$500),WORKDAY(A110,E110,Dias_Sem_Compensacao!$A$2:$A$500)),"") -> 46296 | H110: 0 | I110: 46295 | J110: JEFERSON LUIS SANTOS DOS SANTOS | K110: 221437
A111: 46295 | B111: BANRISUL COBRANCA | C111: 100 | D111: CLIENTES | E111: =IF(LEFT(D111,6)="CLIENT",IFERROR(VLOOKUP(C111,Config_Carteiras!$A:$B,2,FALSE),1),"") -> 1 | F111: 2084.15 | G111: =IF(LEFT(D111,6)="CLIENT",IF(E111=0,WORKDAY(A111-1,1,Dias_Sem_Compensacao!$A$2:$A$500),WORKDAY(A111,E111,Dias_Sem_Compensacao!$A$2:$A$500)),"") -> 46296 | H111: 0 | I111: 46295 | J111: JULIANO BARRETO GUILANZONI | K111: 219984
A112: 46295 | B112: BANRISUL COBRANCA | C112: 100 | D112: CLIENTES | E112: =IF(LEFT(D112,6)="CLIENT",IFERROR(VLOOKUP(C112,Config_Carteiras!$A:$B,2,FALSE),1),"") -> 1 | F112: 840 | G112: =IF(LEFT(D112,6)="CLIENT",IF(E112=0,WORKDAY(A112-1,1,Dias_Sem_Compensacao!$A$2:$A$500),WORKDAY(A112,E112,Dias_Sem_Compensacao!$A$2:$A$500)),"") -> 46296 | H112: 0 | I112: 46295 | J112: LA FERROVIA PIZZAS LTDA | K112: 220541
A113: 46295 | B113: BANRISUL COBRANCA | C113: 100 | D113: CLIENTES | E113: =IF(LEFT(D113,6)="CLIENT",IFERROR(VLOOKUP(C113,Config_Carteiras!$A:$B,2,FALSE),1),"") -> 1 | F113: 605.38 | G113: =IF(LEFT(D113,6)="CLIENT",IF(E113=0,WORKDAY(A113-1,1,Dias_Sem_Compensacao!$A$2:$A$500),WORKDAY(A113,E113,Dias_Sem_Compensacao!$A$2:$A$500)),"") -> 46296 | H113: 0 | I113: 46295 | J113: LORENI DA SILVA DIAS & CIA. LTDA. | K113: 221159
A114: 46295 | B114: BANRISUL COBRANCA | C114: 100 | D114: CLIENTES | E114: =IF(LEFT(D114,6)="CLIENT",IFERROR(VLOOKUP(C114,Config_Carteiras!$A:$B,2,FALSE),1),"") -> 1 | F114: 388.12 | G114: =IF(LEFT(D114,6)="CLIENT",IF(E114=0,WORKDAY(A114-1,1,Dias_Sem_Compensacao!$A$2:$A$500),WORKDAY(A114,E114,Dias_Sem_Compensacao!$A$2:$A$500)),"") -> 46296 | H114: 0 | I114: 46295 | J114: MARINA L RITTER & FILHO LTDA | K114: 220824
A115: 46295 | B115: BANRISUL COBRANCA | C115: 100 | D115: CLIENTES | E115: =IF(LEFT(D115,6)="CLIENT",IFERROR(VLOOKUP(C115,Config_Carteiras!$A:$B,2,FALSE),1),"") -> 1 | F115: 1247.25 | G115: =IF(LEFT(D115,6)="CLIENT",IF(E115=0,WORKDAY(A115-1,1,Dias_Sem_Compensacao!$A$2:$A$500),WORKDAY(A115,E115,Dias_Sem_Compensacao!$A$2:$A$500)),"") -> 46296 | H115: 0 | I115: 46295 | J115: MERCADO SEHN E SCHWINN LTDA | K115: 219952
A116: 46295 | B116: BANRISUL COBRANCA | C116: 100 | D116: CLIENTES | E116: =IF(LEFT(D116,6)="CLIENT",IFERROR(VLOOKUP(C116,Config_Carteiras!$A:$B,2,FALSE),1),"") -> 1 | F116: 452.29 | G116: =IF(LEFT(D116,6)="CLIENT",IF(E116=0,WORKDAY(A116-1,1,Dias_Sem_Compensacao!$A$2:$A$500),WORKDAY(A116,E116,Dias_Sem_Compensacao!$A$2:$A$500)),"") -> 46296 | H116: 0 | I116: 46295 | J116: MICHEL ANDRE CARVALHO MACIEL | K116: 221179
A117: 46295 | B117: BANRISUL COBRANCA | C117: 100 | D117: CLIENTES | E117: =IF(LEFT(D117,6)="CLIENT",IFERROR(VLOOKUP(C117,Config_Carteiras!$A:$B,2,FALSE),1),"") -> 1 | F117: 1922 | G117: =IF(LEFT(D117,6)="CLIENT",IF(E117=0,WORKDAY(A117-1,1,Dias_Sem_Compensacao!$A$2:$A$500),WORKDAY(A117,E117,Dias_Sem_Compensacao!$A$2:$A$500)),"") -> 46296 | H117: 0 | I117: 46295 | J117: MINI MERCADO E ACOUGUE CRISTIANO E SANDRO LTDA. | K117: 220548
... A120: 46295 | B120: BANRISUL COBRANCA | C120: 100 | D120: CLIENTES | E120: =IF(LEFT(D120,6)="CLIENT",IFERROR(VLOOKUP(C120,Config_Carteiras!$A:$B,2,FALSE),1),"") -> 1 | F120: 969 | G120: =IF(LEFT(D120,6)="CLIENT",IF(E120=0,WORKDAY(A120-1,1,Dias_Sem_Compensacao!$A$2:$A$500),WORKDAY(A120,E120,Dias_Sem_Compensacao!$A$2:$A$500)),"") -> 46296 | H120: 0 | I120: 46295 | J120: NEUSA MARIA ZELINSKI | K120: 220572
A121: 46295 | B121: BANRISUL COBRANCA | C121: 100 | D121: CLIENTES | E121: =IF(LEFT(D121,6)="CLIENT",IFERROR(VLOOKUP(C121,Config_Carteiras!$A:$B,2,FALSE),1),"") -> 1 | F121: 621 | G121: =IF(LEFT(D121,6)="CLIENT",IF(E121=0,WORKDAY(A121-1,1,Dias_Sem_Compensacao!$A$2:$A$500),WORKDAY(A121,E121,Dias_Sem_Compensacao!$A$2:$A$500)),"") -> 46296 | H121: 0 | I121: 46295 | K121: 221124
A122: 46295 | B122: BANRISUL COBRANCA | C122: 100 | D122: CLIENTES | E122: =IF(LEFT(D122,6)="CLIENT",IFERROR(VLOOKUP(C122,Config_Carteiras!$A:$B,2,FALSE),1),"") -> 1 | F122: 297 | G122: =IF(LEFT(D122,6)="CLIENT",IF(E122=0,WORKDAY(A122-1,1,Dias_Sem_Compensacao!$A$2:$A$500),WORKDAY(A122,E122,Dias_Sem_Compensacao!$A$2:$A$500)),"") -> 46296 | H122: 0 | I122: 46295 | J122: PADARIA E CONFEITARIA DO PALHACINHO LTDA | K122: 221467
A123: 46295 | B123: BANRISUL COBRANCA | C123: 100 | D123: CLIENTES | E123: =IF(LEFT(D123,6)="CLIENT",IFERROR(VLOOKUP(C123,Config_Carteiras!$A:$B,2,FALSE),1),"") -> 1 | F123: 599 | G123: =IF(LEFT(D123,6)="CLIENT",IF(E123=0,WORKDAY(A123-1,1,Dias_Sem_Compensacao!$A$2:$A$500),WORKDAY(A123,E123,Dias_Sem_Compensacao!$A$2:$A$500)),"") -> 46296 | H123: 0 | I123: 46295 | J123: PADARIA INDUSTRIAL LTDA | K123: 220610
A124: 46295 | B124: BANRISUL COBRANCA | C124: 100 | D124: CLIENTES | E124: =IF(LEFT(D124,6)="CLIENT",IFERROR(VLOOKUP(C124,Config_Carteiras!$A:$B,2,FALSE),1),"") -> 1 | F124: 442 | G124: =IF(LEFT(D124,6)="CLIENT",IF(E124=0,WORKDAY(A124-1,1,Dias_Sem_Compensacao!$A$2:$A$500),WORKDAY(A124,E124,Dias_Sem_Compensacao!$A$2:$A$500)),"") -> 46296 | H124: 0 | I124: 46295 | K124: 221181
A125: 46295 | B125: BANRISUL COBRANCA | C125: 100 | D125: CLIENTES | E125: =IF(LEFT(D125,6)="CLIENT",IFERROR(VLOOKUP(C125,Config_Carteiras!$A:$B,2,FALSE),1),"") -> 1 | F125: 2084.15 | G125: =IF(LEFT(D125,6)="CLIENT",IF(E125=0,WORKDAY(A125-1,1,Dias_Sem_Compensacao!$A$2:$A$500),WORKDAY(A125,E125,Dias_Sem_Compensacao!$A$2:$A$500)),"") -> 46296 | H125: 0 | I125: 46295 | J125: PADARIA QUE DELICIA PAES LTDA | K125: 219981
A126: 46295 | B126: BANRISUL COBRANCA | C126: 100 | D126: CLIENTES | E126: =IF(LEFT(D126,6)="CLIENT",IFERROR(VLOOKUP(C126,Config_Carteiras!$A:$B,2,FALSE),1),"") -> 1 | F126: 900 | G126: =IF(LEFT(D126,6)="CLIENT",IF(E126=0,WORKDAY(A126-1,1,Dias_Sem_Compensacao!$A$2:$A$500),WORKDAY(A126,E126,Dias_Sem_Compensacao!$A$2:$A$500)),"") -> 46296 | H126: 0 | I126: 46295 | J126: RODRIGO CRISTIANO MICHALSKI IRGANG | K126: 220800
A127: 46295 | B127: BANRISUL COBRANCA | C127: 100 | D127: CLIENTES | E127: =IF(LEFT(D127,6)="CLIENT",IFERROR(VLOOKUP(C127,Config_Carteiras!$A:$B,2,FALSE),1),"") -> 1 | F127: 1972 | G127: =IF(LEFT(D127,6)="CLIENT",IF(E127=0,WORKDAY(A127-1,1,Dias_Sem_Compensacao!$A$2:$A$500),WORKDAY(A127,E127,Dias_Sem_Compensacao!$A$2:$A$500)),"") -> 46296 | H127: 0 | I127: 46295 | J127: ROSELENE SARTORI DEBESAITIS & CIA. LTDA. | K127: 220545
A128: 46295 | B128: BANRISUL COBRANCA | C128: 100 | D128: CLIENTES | E128: =IF(LEFT(D128,6)="CLIENT",IFERROR(VLOOKUP(C128,Config_Carteiras!$A:$B,2,FALSE),1),"") -> 1 | F128: 404 | G128: =IF(LEFT(D128,6)="CLIENT",IF(E128=0,WORKDAY(A128-1,1,Dias_Sem_Compensacao!$A$2:$A$500),WORKDAY(A128,E128,Dias_Sem_Compensacao!$A$2:$A$500)),"") -> 46296 | H128: 0 | I128: 46295 | J128: S. LISCANO FLORES LTDA | K128: 220616
A129: 46295 | B129: BANRISUL COBRANCA | C129: 100 | D129: CLIENTES | E129: =IF(LEFT(D129,6)="CLIENT",IFERROR(VLOOKUP(C129,Config_Carteiras!$A:$B,2,FALSE),1),"") -> 1 | F129: 465.5 | G129: =IF(LEFT(D129,6)="CLIENT",IF(E129=0,WORKDAY(A129-1,1,Dias_Sem_Compensacao!$A$2:$A$500),WORKDAY(A129,E129,Dias_Sem_Compensacao!$A$2:$A$500)),"") -> 46296 | H129: 0 | I129: 46295 | J129: SABORES DA SERRA PIZZARIA LTDA | K129: 220817
A130: 46295 | B130: BANRISUL COBRANCA | C130: 100 | D130: CLIENTES | E130: =IF(LEFT(D130,6)="CLIENT",IFERROR(VLOOKUP(C130,Config_Carteiras!$A:$B,2,FALSE),1),"") -> 1 | F130: 965 | G130: =IF(LEFT(D130,6)="CLIENT",IF(E130=0,WORKDAY(A130-1,1,Dias_Sem_Compensacao!$A$2:$A$500),WORKDAY(A130,E130,Dias_Sem_Compensacao!$A$2:$A$500)),"") -> 46296 | H130: 0 | I130: 46295 | J130: SANDRA PILGER MANFIO | K130: 220358
A131: 46295 | B131: BANRISUL COBRANCA | C131: 100 | D131: CLIENTES | E131: =IF(LEFT(D131,6)="CLIENT",IFERROR(VLOOKUP(C131,Config_Carteiras!$A:$B,2,FALSE),1),"") -> 1 | F131: 3153 | G131: =IF(LEFT(D131,6)="CLIENT",IF(E131=0,WORKDAY(A131-1,1,Dias_Sem_Compensacao!$A$2:$A$500),WORKDAY(A131,E131,Dias_Sem_Compensacao!$A$2:$A$500)),"") -> 46296 | H131: 0 | I131: 46295 | J131: SILVA ATACAREJO LTDA | K131: 220584
A132: 46295 | B132: BANRISUL COBRANCA | C132: 100 | D132: CLIENTES | E132: =IF(LEFT(D132,6)="CLIENT",IFERROR(VLOOKUP(C132,Config_Carteiras!$A:$B,2,FALSE),1),"") -> 1 | F132: 970 | G132: =IF(LEFT(D132,6)="CLIENT",IF(E132=0,WORKDAY(A132-1,1,Dias_Sem_Compensacao!$A$2:$A$500),WORKDAY(A132,E132,Dias_Sem_Compensacao!$A$2:$A$500)),"") -> 46296 | H132: 0 | I132: 46295 | K132: 220586
A133: 46295 | B133: BANRISUL COBRANCA | C133: 100 | D133: CLIENTES | E133: =IF(LEFT(D133,6)="CLIENT",IFERROR(VLOOKUP(C133,Config_Carteiras!$A:$B,2,FALSE),1),"") -> 1 | F133: 1529 | G133: =IF(LEFT(D133,6)="CLIENT",IF(E133=0,WORKDAY(A133-1,1,Dias_Sem_Compensacao!$A$2:$A$500),WORKDAY(A133,E133,Dias_Sem_Compensacao!$A$2:$A$500)),"") -> 46296 | H133: 0 | I133: 46295 | K133: 220785
A134: 46295 | B134: BANRISUL COBRANCA | C134: 100 | D134: CLIENTES | E134: =IF(LEFT(D134,6)="CLIENT",IFERROR(VLOOKUP(C134,Config_Carteiras!$A:$B,2,FALSE),1),"") -> 1 | F134: 880 | G134: =IF(LEFT(D134,6)="CLIENT",IF(E134=0,WORKDAY(A134-1,1,Dias_Sem_Compensacao!$A$2:$A$500),WORKDAY(A134,E134,Dias_Sem_Compensacao!$A$2:$A$500)),"") -> 46296 | H134: 0 | I134: 46295 | K134: 220787
A135: 46295 | B135: BANRISUL COBRANCA | C135: 100 | D135: CLIENTES | E135: =IF(LEFT(D135,6)="CLIENT",IFERROR(VLOOKUP(C135,Config_Carteiras!$A:$B,2,FALSE),1),"") -> 1 | F135: 1491 | G135: =IF(LEFT(D135,6)="CLIENT",IF(E135=0,WORKDAY(A135-1,1,Dias_Sem_Compensacao!$A$2:$A$500),WORKDAY(A135,E135,Dias_Sem_Compensacao!$A$2:$A$500)),"") -> 46296 | H135: 0 | I135: 46295 | J135: SPODE E CIA LTDA. | K135: 221161
A136: 46295 | B136: BANRISUL COBRANCA | C136: 100 | D136: CLIENTES | E136: =IF(LEFT(D136,6)="CLIENT",IFERROR(VLOOKUP(C136,Config_Carteiras!$A:$B,2,FALSE),1),"") -> 1 | F136: 1459 | G136: =IF(LEFT(D136,6)="CLIENT",IF(E136=0,WORKDAY(A136-1,1,Dias_Sem_Compensacao!$A$2:$A$500),WORKDAY(A136,E136,Dias_Sem_Compensacao!$A$2:$A$500)),"") -> 46296 | H136: 0 | I136: 46295 | J136: SUPERMERCADO DENTI LTDA | K136: 221089
A137: 46295 | B137: BANRISUL COBRANCA | C137: 100 | D137: CLIENTES | E137: =IF(LEFT(D137,6)="CLIENT",IFERROR(VLOOKUP(C137,Config_Carteiras!$A:$B,2,FALSE),1),"") -> 1 | F137: 1257 | G137: =IF(LEFT(D137,6)="CLIENT",IF(E137=0,WORKDAY(A137-1,1,Dias_Sem_Compensacao!$A$2:$A$500),WORKDAY(A137,E137,Dias_Sem_Compensacao!$A$2:$A$500)),"") -> 46296 | H137: 0 | I137: 46295 | J137: SUPERMERCADO RORATTO E RODRIGUES LTDA | K137: 220543
A138: 46295 | B138: BANRISUL COBRANCA | C138: 100 | D138: CLIENTES | E138: =IF(LEFT(D138,6)="CLIENT",IFERROR(VLOOKUP(C138,Config_Carteiras!$A:$B,2,FALSE),1),"") -> 1 | F138: 405.6 | G138: =IF(LEFT(D138,6)="CLIENT",IF(E138=0,WORKDAY(A138-1,1,Dias_Sem_Compensacao!$A$2:$A$500),WORKDAY(A138,E138,Dias_Sem_Compensacao!$A$2:$A$500)),"") -> 46296 | H138: 0 | I138: 46295 | J138: SUPERMERCADO SAURESSING LTDA | K138: 221464
A139: 46295 | B139: BANRISUL COBRANCA | C139: 100 | D139: CLIENTES | E139: =IF(LEFT(D139,6)="CLIENT",IFERROR(VLOOKUP(C139,Config_Carteiras!$A:$B,2,FALSE),1),"") -> 1 | F139: 656 | G139: =IF(LEFT(D139,6)="CLIENT",IF(E139=0,WORKDAY(A139-1,1,Dias_Sem_Compensacao!$A$2:$A$500),WORKDAY(A139,E139,Dias_Sem_Compensacao!$A$2:$A$500)),"") -> 46296 | H139: 0 | I139: 46295 | J139: SUPERMERCADO TODO DIA LTDA | K139: 220353
A140: 46295 | B140: BANRISUL COBRANCA | C140: 100 | D140: CLIENTES | E140: =IF(LEFT(D140,6)="CLIENT",IFERROR(VLOOKUP(C140,Config_Carteiras!$A:$B,2,FALSE),1),"") -> 1 | F140: 364.96 | G140: =IF(LEFT(D140,6)="CLIENT",IF(E140=0,WORKDAY(A140-1,1,Dias_Sem_Compensacao!$A$2:$A$500),WORKDAY(A140,E140,Dias_Sem_Compensacao!$A$2:$A$500)),"") -> 46296 | H140: 0 | I140: 46295 | J140: THIARLA DA SILVA SILVEIRA | K140: 221170
A141: 46295 | B141: BANRISUL COBRANCA | C141: 100 | D141: CLIENTES | E141: =IF(LEFT(D141,6)="CLIENT",IFERROR(VLOOKUP(C141,Config_Carteiras!$A:$B,2,FALSE),1),"") -> 1 | F141: 840 | G141: =IF(LEFT(D141,6)="CLIENT",IF(E141=0,WORKDAY(A141-1,1,Dias_Sem_Compensacao!$A$2:$A$500),WORKDAY(A141,E141,Dias_Sem_Compensacao!$A$2:$A$500)),"") -> 46296 | H141: 0 | I141: 46295 | J141: TONIJON DOMINGUES DE OLIVEIRA | K141: 220591
A142: 46295 | B142: BANRISUL COBRANCA | C142: 100 | D142: CLIENTES | E142: =IF(LEFT(D142,6)="CLIENT",IFERROR(VLOOKUP(C142,Config_Carteiras!$A:$B,2,FALSE),1),"") -> 1 | F142: 967 | G142: =IF(LEFT(D142,6)="CLIENT",IF(E142=0,WORKDAY(A142-1,1,Dias_Sem_Compensacao!$A$2:$A$500),WORKDAY(A142,E142,Dias_Sem_Compensacao!$A$2:$A$500)),"") -> 46296 | H142: 0 | I142: 46295 | J142: TRESSOLDI VAREJISTA LTDA. | K142: 220812
A143: 46295 | B143: BANRISUL COBRANCA | C143: 100 | D143: CLIENTES | E143: =IF(LEFT(D143,6)="CLIENT",IFERROR(VLOOKUP(C143,Config_Carteiras!$A:$B,2,FALSE),1),"") -> 1 | F143: 992.5 | G143: =IF(LEFT(D143,6)="CLIENT",IF(E143=0,WORKDAY(A143-1,1,Dias_Sem_Compensacao!$A$2:$A$500),WORKDAY(A143,E143,Dias_Sem_Compensacao!$A$2:$A$500)),"") -> 46296 | H143: 0 | I143: 46295 | J143: V. ULRICH SCHMITZ LTDA | K143: 221465
A144: 46295 | B144: BANRISUL COBRANCA | C144: 100 | D144: CLIENTES | E144: =IF(LEFT(D144,6)="CLIENT",IFERROR(VLOOKUP(C144,Config_Carteiras!$A:$B,2,FALSE),1),"") -> 1 | F144: 466.15 | G144: =IF(LEFT(D144,6)="CLIENT",IF(E144=0,WORKDAY(A144-1,1,Dias_Sem_Compensacao!$A$2:$A$500),WORKDAY(A144,E144,Dias_Sem_Compensacao!$A$2:$A$500)),"") -> 46296 | H144: 0 | I144: 46295 | J144: VANDERLEI ROSA DE QUEVEDO 34208097000 | K144: 221165
...
